sited_test_py/CHANGELOG.md
sited_test_py/README_CN.md
sited_test_py/README_EN.md
sited_test_py/__init__.py
sited_test_py/bin.py
sited_test_py/conf.py
sited_test_py/demo.py
sited_test_py/demo.sited.xml
sited_test_py-1.3.2.dist-info/LICENSE
sited_test_py-1.3.2.dist-info/METADATA
sited_test_py-1.3.2.dist-info/WHEEL
sited_test_py-1.3.2.dist-info/entry_points.txt
sited_test_py-1.3.2.dist-info/top_level.txt
sited_test_py-1.3.2.dist-info/RECORD
